torch_sentiment/__init__.py
torch_sentiment/config.py
torch_sentiment/extractor.py
torch_sentiment/loader.py
torch_sentiment/tokenizer.py
torch_sentiment/trainer.py
torch_sentiment/data/__init__.py
torch_sentiment/data/weights.pth
torch_sentiment/data/yelp.dictionary
torch_sentiment/rnn/__init__.py
torch_sentiment/rnn/model.py
torch_sentiment-0.6.0.dist-info/LICENSE
torch_sentiment-0.6.0.dist-info/METADATA
torch_sentiment-0.6.0.dist-info/WHEEL
torch_sentiment-0.6.0.dist-info/top_level.txt
torch_sentiment-0.6.0.dist-info/RECORD
