Metadata-Version: 2.1
Name: torch-sentiment
Version: 0.6.0
Summary: straight forward rnn model
Author-email: Edward Yang <edwardpyang@gmail.com>
License: Copyright (c) 2018-Present Edward Yang
Keywords: rnn,pytorch,nlp,pytorch
Classifier: License :: OSI Approved :: MIT License
Classifier: Programming Language :: Python
Requires-Python: >=3.10
License-File: LICENSE
Requires-Dist: numpy (>=1.24.0)
Requires-Dist: polars (>=0.15.16)
Requires-Dist: pandas (>=1.5.2)
Requires-Dist: torch (>=1.13.1)
Requires-Dist: orjson (>=3.8.5)
Requires-Dist: pyarrow (>=10.0.1)
Requires-Dist: scikit-learn
Requires-Dist: gensim
Requires-Dist: structlog
Requires-Dist: psutil
Provides-Extra: dev
Requires-Dist: black ; extra == 'dev'
Requires-Dist: bumpver ; extra == 'dev'
Requires-Dist: isort ; extra == 'dev'
Requires-Dist: pip-tools ; extra == 'dev'
Requires-Dist: pytest ; extra == 'dev'
